MANIFEST.in
README.md
setup.py
bsub/__init__.py
bsub/__main__.py
bsub/bsub.py
bsub.egg-info/PKG-INFO
bsub.egg-info/SOURCES.txt
bsub.egg-info/dependency_links.txt
bsub.egg-info/top_level.txt