Metadata-Version: 1.1
Name: bsub
Version: 0.3
Summary: submit jobs to LSF with python
Home-page: https://github.com/brentp/bsub
Author: Brent Pedersen, Joe Brown
Author-email: bpederse@gmail.com
License: MIT
Keywords: cluster lsf bsub
Platform: UNKNOWN
Classifier: Development Status :: 3 - Alpha
Classifier: Topic :: Utilities
Classifier: License :: OSI Approved :: MIT License
